lemma/__init__.py
lemma/__main__.py
lemma/input_adapter.py
lemma/lambda_worker.py
lemma/logo.py
lemma/output_adapter.py
lemma/pipeline.py
lemma/settings.py
lemmacli-0.1.0.dist-info/LICENSE
lemmacli-0.1.0.dist-info/METADATA
lemmacli-0.1.0.dist-info/WHEEL
lemmacli-0.1.0.dist-info/entry_points.txt
lemmacli-0.1.0.dist-info/top_level.txt
lemmacli-0.1.0.dist-info/RECORD
