Metadata-Version: 2.1
Name: lemmacli
Version: 0.1.0
Summary: Run commandline tools on AWS Lambda
Home-page: https://github.com/defparam/lemma
Author: defparam
License: Apache 2.0
Classifier: Programming Language :: Python :: 3
Classifier: Operating System :: OS Independent
Requires-Python: >=3.6
License-File: LICENSE
Requires-Dist: requests
